[1,["caRiALBDNGVbNaz9XLVHX5","8bGyj2pGZC3qghPnNoa5p0","d19KDOxqBCLZjIB9CG44qp","1fMZ3vn0lEFofzz2xRFKcA","3882toMc1Kbot6BN8JeDId","acmYrdxZNJt5o/tAJtuG3I","71tbKeZiBKJ54v3sqOuYYi","34sOy1KcFOpYamsUS6zEzb"],["_textureSetter","value"],["cc.SpriteFrame",["cc.AnimationClip",["_name","_duration","sample","wrapMode","curveData"],-1,11]],[[1,0,1,2,3,4,5]],[[[{"name":"idle2","rect":[0,0,100,63],"offset":[0,0],"originalSize":[100,63],"capInsets":[0,0,0,0]}],[0],0,[0],[0],[0]],[[{"name":"idle3","rect":[0,0,100,63],"offset":[0,0],"originalSize":[100,63],"capInsets":[0,0,0,0]}],[0],0,[0],[0],[1]],[[[0,"idle",0.4,10,2,[{},"paths",11,[{},"sprite",11,[{},"comps",11,[{},"cc.Sprite",11,[{},"spriteFrame",12,[[[{"frame":0},"value",6,0],[{"frame":0.1},"value",6,1],[{"frame":0.2},"value",6,2],[{"frame":0.3},"value",6,3]],11,11,11,11]]]]]]]],0,0,[0,0,0,0],[1,1,1,1],[2,3,4,5]],[[{"name":"idle4","rect":[0,0,100,63],"offset":[0,0],"originalSize":[100,63],"capInsets":[0,0,0,0]}],[0],0,[0],[0],[6]],[[{"name":"idle1","rect":[0,0,100,63],"offset":[0,0],"originalSize":[100,63],"capInsets":[0,0,0,0]}],[0],0,[0],[0],[7]]]]