{"paths":{"0":["wall/wall3",1],"1":["gold/gold2",1],"2":["gold/gold3",1],"3":["lava/annimation/danger1",1],"4":["gold/gold1",1],"5":["wall/wall1",1],"6":["bg/background",1],"7":["lava/annimation/danger3",1],"8":["crack2",1],"9":["lava/danger",1],"10":["wall/wall2",1],"11":["crack",1],"12":["bg/startBg",1],"13":["lava/annimation/danger2",1],"14":["lava/annimation/danger1",0,1],"15":["bg/background",0,1],"16":["crack",0,1],"17":["bg/startBg",0,1],"18":["gold/gold1",0,1],"19":["lava/annimation/danger3",0,1],"20":["gold/gold3",0,1],"21":["crack2",0,1],"22":["wall/wall3",0,1],"23":["wall/wall1",0,1],"24":["gold/gold2",0,1],"25":["lava/annimation/danger2",0,1],"26":["wall/wall2",0,1],"27":["lava/danger",0,1]},"types":["cc.SpriteFrame","cc.Texture2D"],"uuids":["09ZFRBM6ZDhZS0MiLN+SbM","16lgKYHSpCp51s+Tcc8p68","27Ng+y/k1KWqUj8R1DVpjm","3fHMPblHZK9Kp/fYiVr/uL","50OWZNSGlEgICWwZomhZMO","5fUC08Al5Ax6WJ/eejqMD8","61Uv3+2YlJirT9piYvbvmz","69uVcywoZLFIkzGDS+n/zY","6cIZwIFQ9I5aKQ6BQtjtPy","9a4iF6mjZL0Ids7atOZXp5","c0uv9sWeNJ46tFDoC6s5z0","d5g5A3i9tIX72CiNxyu3G3","e3ip+4omJGiY+is5JlNED9","eftzyllOhIS6hCDRWnc572","14ZQ0gAGhBr4rsznit6YWP","47hPPo97JCF52H3EWLGSUf","4ct+o1bfNFzpgpEB93mWVg","5ee92U6hhJeJTXsanEiwkA","62p536f6JKHLpW8F1t1GT/","8efnhYEOJF655IaSQzxTl4","9dfSPvrehDcIgRs8j2But9","aaUOxLcAJDhI224NCHG9iY","b4zH7m4I9Eh4Iy1ChP7ncT","beeMjORslO4ax+GHXrpk2p","c0EcxMK79Lf6OxCAzmy63k","c5KxBnrQVFOqHhvDzWByQP","cayhHTP3RM4K0mAWUm40ut","d6em/dPmZP04Bw/x7o9L4l"],"scenes":{},"redirect":[],"deps":[],"packs":{"03d6306d1":[0,1,2,3,4,5,6,7,8,9,10,11,12,13]},"name":"objects_zhadan","importBase":"import","nativeBase":"native","debug":false,"isZip":false,"encrypted":false,"versions":{"import":["03d6306d1","60890",14,"6c6c5",15,"f7a78",16,"4b868",17,"5a5ec",18,"d4e4d",19,"1791f",20,"a60ce",21,"74dda",22,"abf11",23,"6376f",24,"8ef63",25,"a411b",26,"64bd0",27,"74010"],"native":[0,"a0d3a",1,"3ed33",2,"b851f",3,"65074",4,"8234e",5,"43f14",6,"f9da6",7,"334a4",8,"8067c",9,"f8edb",10,"389af",11,"8067c",12,"c0e1a",13,"a66ea"]}}